{
  "updated": "2026-06-02",
  "status": "mixed",
  "status_label": "Truce Holding — 10% Reciprocal Levy Remains; Section 301 Pending",
  "status_note": "US-China ag trade remains under the Oct 30, 2025 Busan truce (reciprocal-tariff suspension extended through Nov 10, 2026). China TERMINATED its March 2025 ag-specific retaliatory tariffs (15% chicken/wheat/corn/cotton; 10% soybeans/pork/sorghum/etc.) effective Nov 10, 2025, AND suspended the 24% additional tariff — but RETAINED a 10% reciprocal levy on all US goods. Net effect: US grain/oilseed/pork still face MFN + 10% (e.g., soybeans 13%, per Reuters). Section 301 investigations (excess capacity + forced labor, opened Mar 17, 2026) are pending, with a USTR tariff decision targeted around July 24, 2026 — a live re-escalation risk. On May 6, 2026 USTR also opened the second four-year review of the 2018 Section 301 tariffs (comments May 7–Jul 5, 2026). VERIFY in-quota/out-of-quota (TRQ) treatment and any product-specific exclusions against USDA FAS GAIN and the Federal Register before any trading decision.",
  "headline": "China ag-tariff truce holding post-Busan, but a 10% reciprocal levy remains (soybeans 13%) and Section 301 investigations pending a ~July 24 decision keep re-escalation on the table.",
  "rows": [
    {
      "commodity": "Soybeans",
      "icon": "\ud83e\uded8",
      "destination": "China",
      "rate": "13%",
      "baseline": "3% (MFN)",
      "status": "mixed",
      "note": "3% MFN + 10% retained reciprocal levy. The March 2025 retaliatory 10% was terminated Nov 10, 2025 under the Busan truce, but China kept a 10% levy on all US goods; Reuters reports soybeans remain at 13%. Section 301 (Apr 28 hearings) could re-escalate. Verify TRQ/exclusions via USDA FAS GAIN.",
      "effective": "2025-11-10",
      "source_url": "https://www.profarmer.com/news/policy-update/policy-updates-china-suspends-24-tariffs-u-s-goods-keeps-10-levy-and-13-tariff-u-s-soybeans"
    },
    {
      "commodity": "Corn",
      "icon": "\ud83c\udf3d",
      "destination": "China",
      "rate": "11%",
      "baseline": "1% (MFN in-quota)",
      "status": "mixed",
      "note": "1% in-quota MFN + 10% retained reciprocal levy. The March 2025 retaliatory 15% was terminated Nov 10, 2025; the 10% all-goods levy remains. Out-of-quota corn carries a much higher TRQ rate (~65%) before the 10% \u2014 confirm your quota status. China corn purchases remain minimal. Verify via USDA FAS GAIN.",
      "effective": "2025-11-10",
      "source_url": "https://www.fas.usda.gov/data/china-china-reduces-tariff-rates-us-agricultural-products"
    },
    {
      "commodity": "Wheat",
      "icon": "\ud83c\udf3e",
      "destination": "China",
      "rate": "11%",
      "baseline": "1% (MFN in-quota)",
      "status": "mixed",
      "note": "1% in-quota MFN + 10% retained reciprocal levy. March 2025 retaliatory 15% terminated Nov 10, 2025; 10% all-goods levy remains. Out-of-quota wheat carries a much higher TRQ rate (~65%) before the 10%. Minimal China wheat demand. Verify via USDA FAS GAIN.",
      "effective": "2025-11-10",
      "source_url": "https://www.fas.usda.gov/data/china-china-reduces-tariff-rates-us-agricultural-products"
    },
    {
      "commodity": "Pork",
      "icon": "\ud83d\udc16",
      "destination": "China",
      "rate": "22%",
      "baseline": "12% (MFN)",
      "status": "mixed",
      "note": "~12% MFN + 10% retained reciprocal levy. March 2025 retaliatory 10% terminated Nov 10, 2025; 10% all-goods levy remains. China remains a major US pork/offal market. Confirm the exact MFN base and any exclusions via USDA FAS GAIN.",
      "effective": "2025-11-10",
      "source_url": "https://www.porkbusiness.com/ag-policy/china-tariff-reduction-win-u-s-pig-farmers"
    },
    {
      "commodity": "Soybeans",
      "icon": "\ud83e\uded8",
      "destination": "Canada / Mexico",
      "rate": "0%",
      "baseline": "0%",
      "status": "normal",
      "note": "USMCA-compliant, duty-free. USMCA exemption share reached ~86% of Canada/Mexico imports by early 2026. Soybean groups have urged USTR to exempt Canada/Mexico from any Section 301 remedies.",
      "effective": "2020-07-01",
      "source_url": "https://ustr.gov/trade-agreements/free-trade-agreements/united-states-mexico-canada-agreement"
    },
    {
      "commodity": "Corn",
      "icon": "\ud83c\udf3d",
      "destination": "Canada / Mexico",
      "rate": "0%",
      "baseline": "0%",
      "status": "normal",
      "note": "USMCA-compliant, duty-free. Mexico remains the top US corn export destination; Canadian demand steady.",
      "effective": "2020-07-01",
      "source_url": "https://ustr.gov/trade-agreements/free-trade-agreements/united-states-mexico-canada-agreement"
    },
    {
      "commodity": "Ethanol",
      "icon": "\u26fd",
      "destination": "EU",
      "rate": "\u20ac83-192/m\u00b3",
      "baseline": "\u20ac83/mt (2013)",
      "status": "mixed",
      "note": "EU anti-dumping duty on US undenatured ethanol in place since 2013 (\u20ac83.03/metric ton base); some member states apply higher max rates up to \u20ac192/m\u00b3. UK-US deal (May 2025) opened a 1.4B L/yr duty-free quota for the UK only. Verify member-state customs for specific shipments.",
      "effective": "2013-02-01",
      "source_url": "https://policy.trade.ec.europa.eu/enforcement-and-protection/trade-defence/actions-against-imports-into-eu_en"
    }
  ],
  "timeline": [
    {
      "date": "2026-05-06",
      "event": "USTR opens its second statutory four-year review of the 2018 Section 301 tariffs on Chinese imports; domestic-industry comment window May 7\u2013Jul 5, 2026.",
      "impact": "medium",
      "source_url": "https://ustr.gov/"
    },
    {
      "date": "2026-04-28",
      "event": "USTR Section 301 hearings (excess capacity + forced labor) held; tariff decision targeted around July 24, 2026 \u2014 soybean groups warn remedies could trigger renewed Chinese retaliation.",
      "impact": "high",
      "source_url": "https://www.feedstuffs.com/policy/ustr-urged-to-proceed-with-caution-on-section-301-actions"
    },
    {
      "date": "2026-03-17",
      "event": "USTR initiates Section 301 investigations into China and other partners over 'excess capacity' and 'forced labor.'",
      "impact": "medium",
      "source_url": "https://ustr.gov/"
    },
    {
      "date": "2026-02-24",
      "event": "Section 122 global 10% tariff takes effect (150-day measure) after IEEPA tariffs are terminated.",
      "impact": "high",
      "source_url": "https://www.federalregister.gov/agencies/trade-representative-office-of-united-states"
    },
    {
      "date": "2026-02-20",
      "event": "US Supreme Court rules IEEPA does not authorize tariff imposition; April 2025 reciprocal tariffs voided; CBP refund process begins.",
      "impact": "high",
      "source_url": "https://www.supremecourt.gov/"
    },
    {
      "date": "2025-11-10",
      "event": "China terminates its March 2025 ag-specific retaliatory tariffs (15% chicken/wheat/corn/cotton; 10% soybeans/pork/etc.) and suspends the 24% additional tariff \u2014 but RETAINS a 10% reciprocal levy on all US goods (soybeans remain at 13%).",
      "impact": "high",
      "source_url": "https://www.fas.usda.gov/data/china-china-reduces-tariff-rates-us-agricultural-products"
    },
    {
      "date": "2025-10-30",
      "event": "Trump-Xi meeting in Busan: reciprocal-tariff suspension extended through Nov 10, 2026; China commits to 25 MMT/yr US soybean purchases 2026\u20132028 plus $17B/yr other ag.",
      "impact": "high",
      "source_url": "https://www.whitehouse.gov/fact-sheets/2025/11/fact-sheet-president-donald-j-trump-strikes-deal-on-economic-and-trade-relations-with-china/"
    },
    {
      "date": "2025-03-04",
      "event": "China imposes first-tranche retaliatory tariffs on US ag (15% wheat/corn/cotton/chicken; 10% soybeans/pork/etc.) \u2014 later terminated under the Busan truce.",
      "impact": "medium",
      "source_url": "https://www.fas.usda.gov/data/china-sctc-announces-retaliatory-tariffs-us-agricultural-products"
    }
  ]
}
