{
  "fetched": "2026-06-17T15:23:49Z",
  "ok": 47,
  "failed": 0,
  "stale_keys": [],
  "quotes": {
    "corn": {
      "ticker": "ZC=F",
      "close": 417.25,
      "open": 413.0,
      "netChange": 4.25,
      "pctChange": 1.0291,
      "wk52_hi": 481.75,
      "wk52_lo": 368.75
    },
    "corn-dec": {
      "ticker": "ZCZ26.CBT",
      "close": 445.75,
      "open": 442.0,
      "netChange": 3.75,
      "pctChange": 0.8484,
      "wk52_hi": 506.5,
      "wk52_lo": 434.25
    },
    "beans": {
      "ticker": "ZS=F",
      "close": 1150.0,
      "open": 1152.0,
      "netChange": -2.0,
      "pctChange": -0.1736,
      "wk52_hi": 1223.25,
      "wk52_lo": 960.75
    },
    "beans-nov": {
      "ticker": "ZSX26.CBT",
      "close": 1150.0,
      "open": 1152.0,
      "netChange": -2.0,
      "pctChange": -0.1736,
      "wk52_hi": 1214.0,
      "wk52_lo": 1037.5
    },
    "wheat": {
      "ticker": "ZW=F",
      "close": 616.25,
      "open": 604.5,
      "netChange": 11.75,
      "pctChange": 1.9438,
      "wk52_hi": 679.5,
      "wk52_lo": 492.25
    },
    "oats": {
      "ticker": "ZO=F",
      "close": 306.75,
      "open": 309.5,
      "netChange": -2.75,
      "pctChange": -0.8885,
      "wk52_hi": 403.5,
      "wk52_lo": 272.0
    },
    "corn-jul26": {
      "ticker": "ZCN26.CBT",
      "close": 417.25,
      "open": 413.0,
      "netChange": 4.25,
      "pctChange": 1.0291,
      "wk52_hi": 487.5,
      "wk52_lo": 406.25
    },
    "corn-sep26": {
      "ticker": "ZCU26.CBT",
      "close": 426.0,
      "open": 422.25,
      "netChange": 3.75,
      "pctChange": 0.8881,
      "wk52_hi": 492.0,
      "wk52_lo": 414.5
    },
    "corn-mar27": {
      "ticker": "ZCH27.CBT",
      "close": 460.25,
      "open": 456.5,
      "netChange": 3.75,
      "pctChange": 0.8215,
      "wk52_hi": 519.5,
      "wk52_lo": 448.5
    },
    "corn-may27": {
      "ticker": "ZCK27.CBT",
      "close": 469.25,
      "open": 465.75,
      "netChange": 3.5,
      "pctChange": 0.7515,
      "wk52_hi": 526.25,
      "wk52_lo": 458.0
    },
    "corn-jul27": {
      "ticker": "ZCN27.CBT",
      "close": 475.5,
      "open": 472.5,
      "netChange": 3.0,
      "pctChange": 0.6349,
      "wk52_hi": 529.75,
      "wk52_lo": 463.5
    },
    "corn-dec27": {
      "ticker": "ZCZ27.CBT",
      "close": 475.25,
      "open": 472.25,
      "netChange": 3.0,
      "pctChange": 0.6353,
      "wk52_hi": 513.75,
      "wk52_lo": 451.75
    },
    "beans-jul26": {
      "ticker": "ZSN26.CBT",
      "close": 1132.0,
      "open": 1136.25,
      "netChange": -4.25,
      "pctChange": -0.374,
      "wk52_hi": 1250.75,
      "wk52_lo": 1043.0
    },
    "beans-aug26": {
      "ticker": "ZSQ26.CBT",
      "close": 1137.0,
      "open": 1140.5,
      "netChange": -3.5,
      "pctChange": -0.3069,
      "wk52_hi": 1231.0,
      "wk52_lo": 1044.5
    },
    "beans-sep26": {
      "ticker": "ZSU26.CBT",
      "close": 1136.5,
      "open": 1138.5,
      "netChange": -2.0,
      "pctChange": -0.1757,
      "wk52_hi": 1209.5,
      "wk52_lo": 1035.75
    },
    "beans-jan27": {
      "ticker": "ZSF27.CBT",
      "close": 1163.25,
      "open": 1165.75,
      "netChange": -2.5,
      "pctChange": -0.2145,
      "wk52_hi": 1225.25,
      "wk52_lo": 1050.0
    },
    "beans-mar27": {
      "ticker": "ZSH27.CBT",
      "close": 1170.0,
      "open": 1171.75,
      "netChange": -1.75,
      "pctChange": -0.1493,
      "wk52_hi": 1221.0,
      "wk52_lo": 1053.75
    },
    "beans-jul27": {
      "ticker": "ZSN27.CBT",
      "close": 1184.75,
      "open": 1186.5,
      "netChange": -1.75,
      "pctChange": -0.1475,
      "wk52_hi": 1226.25,
      "wk52_lo": 1067.25
    },
    "beans-nov27": {
      "ticker": "ZSX27.CBT",
      "close": 1135.0,
      "open": 1135.5,
      "netChange": -0.5,
      "pctChange": -0.044,
      "wk52_hi": 1160.25,
      "wk52_lo": 1050.5
    },
    "wheat-jul26": {
      "ticker": "ZWN26.CBT",
      "close": 607.5,
      "open": 595.25,
      "netChange": 12.25,
      "pctChange": 2.058,
      "wk52_hi": 688.25,
      "wk52_lo": 525.75
    },
    "wheat-sep26": {
      "ticker": "ZWU26.CBT",
      "close": 616.0,
      "open": 604.5,
      "netChange": 11.5,
      "pctChange": 1.9024,
      "wk52_hi": 700.0,
      "wk52_lo": 539.75
    },
    "wheat-dec26": {
      "ticker": "ZWZ26.CBT",
      "close": 633.25,
      "open": 622.25,
      "netChange": 11.0,
      "pctChange": 1.7678,
      "wk52_hi": 718.0,
      "wk52_lo": 557.25
    },
    "wheat-mar27": {
      "ticker": "ZWH27.CBT",
      "close": 647.5,
      "open": 638.25,
      "netChange": 9.25,
      "pctChange": 1.4493,
      "wk52_hi": 732.0,
      "wk52_lo": 572.5
    },
    "wheat-jul27": {
      "ticker": "ZWN27.CBT",
      "close": 661.75,
      "open": 654.0,
      "netChange": 7.75,
      "pctChange": 1.185,
      "wk52_hi": 729.0,
      "wk52_lo": 583.5
    },
    "wheat-dec27": {
      "ticker": "ZWZ27.CBT",
      "close": 688.5,
      "open": 682.25,
      "netChange": 6.25,
      "pctChange": 0.9161,
      "wk52_hi": 741.0,
      "wk52_lo": 607.25
    },
    "cattle": {
      "ticker": "LE=F",
      "close": 247.97501,
      "open": 249.125,
      "netChange": -1.14999,
      "pctChange": -0.4616,
      "wk52_hi": 258.725,
      "wk52_lo": 204.55
    },
    "feeders": {
      "ticker": "GF=F",
      "close": 364.77499,
      "open": 367.625,
      "netChange": -2.85001,
      "pctChange": -0.7752,
      "wk52_hi": 381.025,
      "wk52_lo": 299.525
    },
    "hogs": {
      "ticker": "HE=F",
      "close": 95.875,
      "open": 95.075,
      "netChange": 0.8,
      "pctChange": 0.8414,
      "wk52_hi": 113.7,
      "wk52_lo": 77.35
    },
    "milk": {
      "ticker": "DC=F",
      "close": 15.95,
      "open": 16.36,
      "netChange": -0.41,
      "pctChange": -2.5061,
      "wk52_hi": 18.79,
      "wk52_lo": 14.53
    },
    "cattle-aug26": {
      "ticker": "LEQ26.CME",
      "close": 247.97501,
      "open": 249.125,
      "netChange": -1.14999,
      "pctChange": -0.4616,
      "wk52_hi": 251.65,
      "wk52_lo": 195.9
    },
    "cattle-oct26": {
      "ticker": "LEV26.CME",
      "close": 240.55,
      "open": 242.075,
      "netChange": -1.525,
      "pctChange": -0.63,
      "wk52_hi": 246.55,
      "wk52_lo": 195.975
    },
    "cattle-dec26": {
      "ticker": "LEZ26.CME",
      "close": 239.10001,
      "open": 240.7,
      "netChange": -1.59999,
      "pctChange": -0.6647,
      "wk52_hi": 245.9,
      "wk52_lo": 196.15
    },
    "cattle-feb27": {
      "ticker": "LEG27.CME",
      "close": 238.97501,
      "open": 240.675,
      "netChange": -1.69999,
      "pctChange": -0.7063,
      "wk52_hi": 245.9,
      "wk52_lo": 196.975
    },
    "cattle-apr27": {
      "ticker": "LEJ27.CME",
      "close": 238.625,
      "open": 240.22501,
      "netChange": -1.60001,
      "pctChange": -0.666,
      "wk52_hi": 245.3,
      "wk52_lo": 196.075
    },
    "cattle-jun27": {
      "ticker": "LEM27.CME",
      "close": 232.0,
      "open": 233.625,
      "netChange": -1.625,
      "pctChange": -0.6956,
      "wk52_hi": 238.625,
      "wk52_lo": 189.675
    },
    "meal": {
      "ticker": "ZM=F",
      "close": 304.29999,
      "open": 307.10001,
      "netChange": -2.80002,
      "pctChange": -0.9118,
      "wk52_hi": 342.7,
      "wk52_lo": 258.6
    },
    "soyoil": {
      "ticker": "ZL=F",
      "close": 67.42,
      "open": 72.45,
      "netChange": -5.03,
      "pctChange": -6.9427,
      "wk52_hi": 79.69,
      "wk52_lo": 47.51
    },
    "crude": {
      "ticker": "CL=F",
      "close": 77.02,
      "open": 74.8,
      "netChange": 2.22,
      "pctChange": 2.9679,
      "wk52_hi": 119.48,
      "wk52_lo": 54.98
    },
    "natgas": {
      "ticker": "NG=F",
      "close": 3.173,
      "open": 3.243,
      "netChange": -0.07,
      "pctChange": -2.1585,
      "wk52_hi": 7.827,
      "wk52_lo": 2.483
    },
    "gold": {
      "ticker": "GC=F",
      "close": 4367.0,
      "open": 4351.2002,
      "netChange": 15.7998,
      "pctChange": 0.3631,
      "wk52_hi": 5586.2002,
      "wk52_lo": 3253.8
    },
    "silver": {
      "ticker": "SI=F",
      "close": 70.43,
      "open": 70.22,
      "netChange": 0.21,
      "pctChange": 0.2991,
      "wk52_hi": 121.3,
      "wk52_lo": 35.27
    },
    "dollar": {
      "ticker": "DX-Y.NYB",
      "close": 99.706,
      "open": 99.53,
      "netChange": 0.176,
      "pctChange": 0.1768,
      "wk52_hi": 100.64,
      "wk52_lo": 95.55
    },
    "treasury10": {
      "ticker": "^TNX",
      "close": 4.438,
      "open": 4.428,
      "netChange": 0.01,
      "pctChange": 0.2258,
      "wk52_hi": 4.687,
      "wk52_lo": 3.947
    },
    "sp500": {
      "ticker": "^GSPC",
      "close": 7509.68994,
      "open": 7512.99023,
      "netChange": -3.30029,
      "pctChange": -0.0439,
      "wk52_hi": 7620.8999,
      "wk52_lo": 5943.23
    },
    "bitcoin": {
      "ticker": "BTC-USD",
      "close": 65283.48047,
      "open": 65616.64844,
      "netChange": -333.16797,
      "pctChange": -0.5077,
      "wk52_hi": 126198.0703,
      "wk52_lo": 59108.918
    },
    "ripple": {
      "ticker": "XRP-USD",
      "close": 1.2009,
      "open": 1.2161,
      "netChange": -0.0152,
      "pctChange": -1.2499,
      "wk52_hi": 3.6502,
      "wk52_lo": 1.0547
    },
    "kaspa": {
      "ticker": "KAS-USD",
      "close": 0.03216,
      "open": 0.03249,
      "netChange": -0.00033,
      "pctChange": -1.0157,
      "wk52_hi": 0.1185,
      "wk52_lo": 0.0139
    }
  }
}