{
  "fetched": "2026-05-18T18:29:30Z",
  "ok": 40,
  "failed": 1,
  "quotes": {
    "corn": {
      "ticker": "ZC=F",
      "close": 477.0,
      "open": 467.5,
      "netChange": 9.5,
      "pctChange": 2.0321,
      "wk52_hi": 475.0,
      "wk52_lo": 368.75
    },
    "corn-dec": {
      "ticker": "ZCZ26.CBT",
      "close": 498.25,
      "open": 492.0,
      "netChange": 6.25,
      "pctChange": 1.2703,
      "wk52_hi": 506.5,
      "wk52_lo": 440.75
    },
    "beans": {
      "ticker": "ZS=F",
      "close": 1212.5,
      "open": 1197.75,
      "netChange": 14.75,
      "pctChange": 1.2315,
      "wk52_hi": 1223.25,
      "wk52_lo": 960.75
    },
    "beans-nov": {
      "ticker": "ZSX26.CBT",
      "close": 1200.0,
      "open": 1192.75,
      "netChange": 7.25,
      "pctChange": 0.6078,
      "wk52_hi": 1214.0,
      "wk52_lo": 1033.75
    },
    "wheat": {
      "ticker": "ZW=F",
      "close": 664.25,
      "open": 653.0,
      "netChange": 11.25,
      "pctChange": 1.7228,
      "wk52_hi": 670.75,
      "wk52_lo": 492.25
    },
    "oats": {
      "ticker": "ZO=F",
      "close": 373.0,
      "open": 368.5,
      "netChange": 4.5,
      "pctChange": 1.2212,
      "wk52_hi": 403.5,
      "wk52_lo": 272.0
    },
    "corn-jul26": {
      "ticker": "ZCN26.CBT",
      "close": 477.0,
      "open": 467.5,
      "netChange": 9.5,
      "pctChange": 2.0321,
      "wk52_hi": 487.5,
      "wk52_lo": 428.5
    },
    "corn-sep26": {
      "ticker": "ZCU26.CBT",
      "close": 482.5,
      "open": 474.75,
      "netChange": 7.75,
      "pctChange": 1.6324,
      "wk52_hi": 492.0,
      "wk52_lo": 431.25
    },
    "corn-mar27": {
      "ticker": "ZCH27.CBT",
      "close": 512.0,
      "open": 506.0,
      "netChange": 6.0,
      "pctChange": 1.1858,
      "wk52_hi": 519.5,
      "wk52_lo": 454.25
    },
    "corn-may27": {
      "ticker": "ZCK27.CBT",
      "close": 518.5,
      "open": 512.25,
      "netChange": 6.25,
      "pctChange": 1.2201,
      "wk52_hi": 526.25,
      "wk52_lo": 461.25
    },
    "corn-jul27": {
      "ticker": "ZCN27.CBT",
      "close": 522.0,
      "open": 516.25,
      "netChange": 5.75,
      "pctChange": 1.1138,
      "wk52_hi": 529.75,
      "wk52_lo": 463.5
    },
    "corn-dec27": {
      "ticker": "ZCZ27.CBT",
      "close": 503.0,
      "open": 502.75,
      "netChange": 0.25,
      "pctChange": 0.0497,
      "wk52_hi": 513.75,
      "wk52_lo": 451.75
    },
    "beans-jul26": {
      "ticker": "ZSN26.CBT",
      "close": 1212.25,
      "open": 1197.75,
      "netChange": 14.5,
      "pctChange": 1.2106,
      "wk52_hi": 1250.75,
      "wk52_lo": 1043.0
    },
    "beans-aug26": {
      "ticker": "ZSQ26.CBT",
      "close": 1210.25,
      "open": 1197.75,
      "netChange": 12.5,
      "pctChange": 1.0436,
      "wk52_hi": 1231.0,
      "wk52_lo": 1044.5
    },
    "beans-sep26": {
      "ticker": "ZSU26.CBT",
      "close": 1194.25,
      "open": 1185.25,
      "netChange": 9.0,
      "pctChange": 0.7593,
      "wk52_hi": 1209.5,
      "wk52_lo": 1035.75
    },
    "beans-jan27": {
      "ticker": "ZSF27.CBT",
      "close": 1210.75,
      "open": 1205.0,
      "netChange": 5.75,
      "pctChange": 0.4772,
      "wk52_hi": 1225.25,
      "wk52_lo": 1045.5
    },
    "beans-mar27": {
      "ticker": "ZSH27.CBT",
      "close": 1207.5,
      "open": 1203.25,
      "netChange": 4.25,
      "pctChange": 0.3532,
      "wk52_hi": 1221.0,
      "wk52_lo": 1046.0
    },
    "beans-jul27": {
      "ticker": "ZSN27.CBT",
      "close": 1213.0,
      "open": 1209.75,
      "netChange": 3.25,
      "pctChange": 0.2687,
      "wk52_hi": 1226.25,
      "wk52_lo": 1059.75
    },
    "beans-nov27": {
      "ticker": "ZSX27.CBT",
      "close": 1147.5,
      "open": 1146.5,
      "netChange": 1.0,
      "pctChange": 0.0872,
      "wk52_hi": 1159.25,
      "wk52_lo": 1043.5
    },
    "wheat-jul26": {
      "ticker": "ZWN26.CBT",
      "close": 664.75,
      "open": 653.0,
      "netChange": 11.75,
      "pctChange": 1.7994,
      "wk52_hi": 688.25,
      "wk52_lo": 525.75
    },
    "wheat-sep26": {
      "ticker": "ZWU26.CBT",
      "close": 678.0,
      "open": 667.25,
      "netChange": 10.75,
      "pctChange": 1.6111,
      "wk52_hi": 700.0,
      "wk52_lo": 539.75
    },
    "wheat-dec26": {
      "ticker": "ZWZ26.CBT",
      "close": 696.5,
      "open": 686.5,
      "netChange": 10.0,
      "pctChange": 1.4567,
      "wk52_hi": 718.0,
      "wk52_lo": 557.25
    },
    "wheat-mar27": {
      "ticker": "ZWH27.CBT",
      "close": 711.0,
      "open": 701.75,
      "netChange": 9.25,
      "pctChange": 1.3181,
      "wk52_hi": 732.0,
      "wk52_lo": 572.5
    },
    "wheat-jul27": {
      "ticker": "ZWN27.CBT",
      "close": 714.5,
      "open": 703.0,
      "netChange": 11.5,
      "pctChange": 1.6358,
      "wk52_hi": 729.0,
      "wk52_lo": 583.5
    },
    "wheat-dec27": {
      "ticker": "ZWZ27.CBT",
      "close": 732.5,
      "open": 709.5,
      "netChange": 23.0,
      "pctChange": 3.2417,
      "wk52_hi": 741.0,
      "wk52_lo": 607.25
    },
    "cattle": {
      "ticker": "LE=F",
      "close": 247.125,
      "open": 247.925,
      "netChange": -0.8,
      "pctChange": -0.3227,
      "wk52_hi": 258.725,
      "wk52_lo": 204.55
    },
    "feeders": {
      "ticker": "GF=F",
      "close": 358.77499,
      "open": 361.45001,
      "netChange": -2.67502,
      "pctChange": -0.7401,
      "wk52_hi": 381.025,
      "wk52_lo": 293.05
    },
    "hogs": {
      "ticker": "HE=F",
      "close": 102.9,
      "open": 103.35,
      "netChange": -0.45,
      "pctChange": -0.4354,
      "wk52_hi": 113.7,
      "wk52_lo": 77.35
    },
    "milk": {
      "ticker": "DC=F",
      "close": 16.95,
      "open": 17.02,
      "netChange": -0.07,
      "pctChange": -0.4113,
      "wk52_hi": 18.89,
      "wk52_lo": 14.53
    },
    "meal": {
      "ticker": "ZM=F",
      "close": 334.79999,
      "open": 339.5,
      "netChange": -4.70001,
      "pctChange": -1.3844,
      "wk52_hi": 342.7,
      "wk52_lo": 258.6
    },
    "soyoil": {
      "ticker": "ZL=F",
      "close": 75.53,
      "open": 74.67,
      "netChange": 0.86,
      "pctChange": 1.1517,
      "wk52_hi": 78.5,
      "wk52_lo": 45.74
    },
    "crude": {
      "ticker": "CL=F",
      "close": 104.12,
      "open": 103.19,
      "netChange": 0.93,
      "pctChange": 0.9013,
      "wk52_hi": 119.48,
      "wk52_lo": 54.98
    },
    "natgas": {
      "ticker": "NG=F",
      "close": 3.025,
      "open": 3.023,
      "netChange": 0.002,
      "pctChange": 0.0662,
      "wk52_hi": 7.827,
      "wk52_lo": 2.483
    },
    "gold": {
      "ticker": "GC=F",
      "close": 4546.5,
      "open": 4546.7998,
      "netChange": -0.2998,
      "pctChange": -0.0066,
      "wk52_hi": 5586.2002,
      "wk52_lo": 3207.5
    },
    "silver": {
      "ticker": "SI=F",
      "close": 77.135,
      "open": 75.555,
      "netChange": 1.58,
      "pctChange": 2.0912,
      "wk52_hi": 121.3,
      "wk52_lo": 32.07
    },
    "dollar": {
      "ticker": "DX=F",
      "close": 100.0,
      "open": 99.873,
      "netChange": 0.127,
      "pctChange": 0.1272
    },
    "treasury10": {
      "ticker": "^TNX",
      "close": 4.609,
      "open": 4.595,
      "netChange": 0.014,
      "pctChange": 0.3047,
      "wk52_hi": 4.629,
      "wk52_lo": 3.947
    },
    "sp500": {
      "ticker": "^GSPC",
      "close": 7365.33984,
      "open": 7409.18018,
      "netChange": -43.84034,
      "pctChange": -0.5917,
      "wk52_hi": 7517.1201,
      "wk52_lo": 5767.4102
    },
    "bitcoin": {
      "ticker": "BTC-USD",
      "close": 76289.63281,
      "open": 77407.59375,
      "netChange": -1117.96094,
      "pctChange": -1.4443,
      "wk52_hi": 126198.0703,
      "wk52_lo": 60074.2031
    },
    "ripple": {
      "ticker": "XRP-USD",
      "close": 1.3696,
      "open": 1.4008,
      "netChange": -0.0312,
      "pctChange": -2.2273,
      "wk52_hi": 3.6502,
      "wk52_lo": 1.1335
    },
    "kaspa": {
      "ticker": "KAS-USD",
      "close": 0.03371,
      "open": 0.03399,
      "netChange": -0.00028,
      "pctChange": -0.8238,
      "wk52_hi": 0.1198,
      "wk52_lo": 0.0139
    }
  }
}